jort/__init__.py
jort/_config.py
jort/_version.py
jort/block.py
jort/checkpoint.py
jort/config.py
jort/database.py
jort/datetime_utils.py
jort/exceptions.py
jort/jort_exe.py
jort/reporting_callbacks.py
jort/track_cli.py
jort/tracker.py
jort-1.5.0.dist-info/LICENSE
jort-1.5.0.dist-info/METADATA
jort-1.5.0.dist-info/WHEEL
jort-1.5.0.dist-info/entry_points.txt
jort-1.5.0.dist-info/top_level.txt
jort-1.5.0.dist-info/RECORD
