Metadata-Version: 2.1
Name: jort
Version: 1.5.0
Summary: Script profiler with checkpoints
Home-page: https://github.com/bbrzycki/jort
Author: Bryan Brzycki
Author-email: bbrzycki@berkeley.edu
Project-URL: Source, https://github.com/bbrzycki/jort
Classifier: Programming Language :: Python :: 3
Classifier: License :: OSI Approved :: MIT License
Classifier: Operating System :: OS Independent
License-File: LICENSE
Requires-Dist: numpy (>=1.18.1)
Requires-Dist: python-dateutil (>=2.8.2)
Requires-Dist: psutil (>=5.9.0)
Requires-Dist: twilio (>=8.2.0)
Requires-Dist: humanfriendly (>=10.0)
Requires-Dist: tqdm (>=4.64.1)
Requires-Dist: sphinx-rtd-theme (==1.2.1)
Requires-Dist: shortuuid (==1.0.11)
Requires-Dist: click (>=8.1.3)
Requires-Dist: pandas (>=1.4.2)
